getcomic/__init__.py
getcomic/getcomic.py
getcomic-2.0.13.dist-info/METADATA
getcomic-2.0.13.dist-info/RECORD
getcomic-2.0.13.dist-info/WHEEL
getcomic-2.0.13.dist-info/entry_points.txt
getcomic-2.0.13.dist-info/top_level.txt
