Metadata-Version: 2.1
Name: getcomic
Version: 2.0.13
Summary: A command line tool to download comics from readcomiconline.to
Home-page: https://github.com/VinitraMk/getcomic-cli
Author: VinitraMk
Author-email: vinitramk@gmail.com
License: UNKNOWN
Platform: UNKNOWN
Classifier: Development Status :: 4 - Beta
Classifier: Intended Audience :: Developers
Classifier: Operating System :: POSIX
Classifier: Programming Language :: Python
Requires-Dist: fpdf
Requires-Dist: selenium
Requires-Dist: pathlib
